clearcv/__init__.py
clearcv/color.py
clearcv/filters.py
clearcv/io.py
clearcv/sample.py
clearcv/transform.py
clearcv/utils.py
clearcv-0.1.0.dist-info/licenses/LICENSE
clearcv-0.1.0.dist-info/METADATA
clearcv-0.1.0.dist-info/WHEEL
clearcv-0.1.0.dist-info/top_level.txt
clearcv-0.1.0.dist-info/RECORD
