Metadata-Version: 2.4
Name: clearcv
Version: 0.1.0
Summary: ClearCV — a lightweight, NumPy-based computer vision toolkit built in Python.
Author: Your Name
Author-email: Your Name <you@example.com>
License: MIT
Keywords: computer-vision,image-processing,numpy,clearcv
Requires-Python: >=3.8
License-File: LICENSE
Requires-Dist: numpy>=1.20
Provides-Extra: extras
Requires-Dist: imageio; extra == "extras"
Requires-Dist: matplotlib; extra == "extras"
Dynamic: author
Dynamic: license-file
Dynamic: requires-python
